fastbackfilter/__init__.py
fastbackfilter/cache.py
fastbackfilter/cli.py
fastbackfilter/core.py
fastbackfilter/detection_schema.json
fastbackfilter/exceptions.py
fastbackfilter/logging_cfg.py
fastbackfilter/registry.py
fastbackfilter/types.py
fastbackfilter/engines/__init__.py
fastbackfilter/engines/base.py
fastbackfilter/engines/bat.py
fastbackfilter/engines/csv.py
fastbackfilter/engines/exe.py
fastbackfilter/engines/fallback.py
fastbackfilter/engines/gzip.py
fastbackfilter/engines/html.py
fastbackfilter/engines/image.py
fastbackfilter/engines/json.py
fastbackfilter/engines/legacy_office.py
fastbackfilter/engines/mp3.py
fastbackfilter/engines/mp4.py
fastbackfilter/engines/pdf.py
fastbackfilter/engines/png.py
fastbackfilter/engines/sh.py
fastbackfilter/engines/tar.py
fastbackfilter/engines/text.py
fastbackfilter/engines/wav.py
fastbackfilter/engines/xml.py
fastbackfilter/engines/zip_office.py
fastbackfilter-1.3.8.dist-info/METADATA
fastbackfilter-1.3.8.dist-info/WHEEL
fastbackfilter-1.3.8.dist-info/entry_points.txt
fastbackfilter-1.3.8.dist-info/top_level.txt
fastbackfilter-1.3.8.dist-info/RECORD
